aiotempfile/__init__.py
aiotempfile/aiotempfile.py
tests/__init__.py
tests/conftest.py
tests/test_aiotempfile.py
aiotempfile-0.5.5.dist-info/LICENSE.md
aiotempfile-0.5.5.dist-info/METADATA
aiotempfile-0.5.5.dist-info/WHEEL
aiotempfile-0.5.5.dist-info/top_level.txt
aiotempfile-0.5.5.dist-info/RECORD
