Metadata-Version: 2.1
Name: aiotempfile
Version: 0.5.5
Summary: Provides asynchronous temporary files.
Home-page: https://github.com/crashvb/aiotempfile
Author: Richard Davis
Author-email: crashvb@gmail.com
License: Apache License 2.0
Project-URL: Bug Reports, https://github.com/crashvb/aiotempfile/issues
Project-URL: Source, https://github.com/crashvb/aiotempfile
Keywords: aio aiotempfile async asynchronous file files temp temporary
Platform: UNKNOWN
Classifier: Development Status :: 5 - Production/Stable
Classifier: Intended Audience :: Developers
Classifier: License :: OSI Approved :: Apache Software License
Classifier: Programming Language :: Python :: 3
Classifier: Programming Language :: Python :: 3.8
Classifier: Programming Language :: Python :: 3.9
Classifier: Programming Language :: Python :: 3.10
Classifier: Operating System :: OS Independent
License-File: LICENSE.md
Requires-Dist: aiofiles<23.2.0
Provides-Extra: dev
Requires-Dist: black; extra == "dev"
Requires-Dist: coveralls; extra == "dev"
Requires-Dist: pylint; extra == "dev"
Requires-Dist: pytest; extra == "dev"
Requires-Dist: pytest-asyncio; extra == "dev"
Requires-Dist: pytest-cov; extra == "dev"
Requires-Dist: twine; extra == "dev"
Requires-Dist: wheel; extra == "dev"
